{"name":"build-javascript","namedChunkGroups":{"polyfill":{"name":"polyfill","assets":[{"name":"webpack-runtime-3ea1dbeb7b399e68c2fc.js","size":4914},{"name":"polyfill-ba498aa985cbf46df0e4.js","size":85015}],"filteredAssets":0,"assetsSize":89929,"filteredAuxiliaryAssets":2,"auxiliaryAssetsSize":229770},"app":{"name":"app","assets":[{"name":"webpack-runtime-3ea1dbeb7b399e68c2fc.js","size":4914},{"name":"framework-0915f7633b7aea95e174.js","size":23171},{"name":"app-07121b9221c6ebf13cef.js","size":132172}],"filteredAssets":0,"assetsSize":160257,"filteredAuxiliaryAssets":3,"auxiliaryAssetsSize":700192},"component---src-pages-404-tsx":{"name":"component---src-pages-404-tsx","assets":[{"name":"styles.6767fdfb70acbd36d207.css","size":166777},{"name":"cb1608f2-b629d79132906cc15154.js","size":10743},{"name":"f357f4e3-c57b41609a846ff0aa61.js","size":1163},{"name":"commons-ec4ac25f20428eb87e90.js","size":136701},{"name":"component---src-pages-404-tsx-5c9f11fe5ba33965f5e4.js","size":777}],"filteredAssets":0,"assetsSize":316161,"filteredAuxiliaryAssets":78,"auxiliaryAssetsSize":14868450},"component---src-pages-index-tsx":{"name":"component---src-pages-index-tsx","assets":[{"name":"styles.6767fdfb70acbd36d207.css","size":166777},{"name":"cb1608f2-b629d79132906cc15154.js","size":10743},{"name":"a9a7754c-4cb8be3b2291d86156da.js","size":5218},{"name":"commons-ec4ac25f20428eb87e90.js","size":136701},{"name":"component---src-pages-index-tsx-d00045e999b340ebf4df.js","size":5108}],"filteredAssets":0,"assetsSize":324547,"filteredAuxiliaryAssets":78,"auxiliaryAssetsSize":15223951},"component---src-pages-search-tsx":{"name":"component---src-pages-search-tsx","assets":[{"name":"styles.6767fdfb70acbd36d207.css","size":166777},{"name":"cb1608f2-b629d79132906cc15154.js","size":10743},{"name":"commons-ec4ac25f20428eb87e90.js","size":136701},{"name":"component---src-pages-search-tsx-70c5457333e1350174a3.js","size":3034}],"filteredAssets":0,"assetsSize":317255,"filteredAuxiliaryAssets":77,"auxiliaryAssetsSize":14704732},"component---src-pages-tags-tsx":{"name":"component---src-pages-tags-tsx","assets":[{"name":"styles.6767fdfb70acbd36d207.css","size":166777},{"name":"cb1608f2-b629d79132906cc15154.js","size":10743},{"name":"commons-ec4ac25f20428eb87e90.js","size":136701},{"name":"component---src-pages-tags-tsx-a7ae398fa8fb5bc2bcb2.js","size":4251}],"filteredAssets":0,"assetsSize":318472,"filteredAuxiliaryAssets":77,"auxiliaryAssetsSize":14705591},"component---src-templates-post-tsx":{"name":"component---src-templates-post-tsx","assets":[{"name":"styles.6767fdfb70acbd36d207.css","size":166777},{"name":"cb1608f2-b629d79132906cc15154.js","size":10743},{"name":"commons-ec4ac25f20428eb87e90.js","size":136701},{"name":"component---src-templates-post-tsx-67882746e97a6a94cad9.js","size":83944}],"filteredAssets":0,"assetsSize":398165,"filteredAuxiliaryAssets":77,"auxiliaryAssetsSize":15011049}},"assetsByChunkName":{"polyfill":["webpack-runtime-3ea1dbeb7b399e68c2fc.js","polyfill-ba498aa985cbf46df0e4.js"],"app":["webpack-runtime-3ea1dbeb7b399e68c2fc.js","framework-0915f7633b7aea95e174.js","app-07121b9221c6ebf13cef.js"],"component---src-pages-404-tsx":["styles.6767fdfb70acbd36d207.css","cb1608f2-b629d79132906cc15154.js","f357f4e3-c57b41609a846ff0aa61.js","commons-ec4ac25f20428eb87e90.js","component---src-pages-404-tsx-5c9f11fe5ba33965f5e4.js"],"component---src-pages-index-tsx":["styles.6767fdfb70acbd36d207.css","cb1608f2-b629d79132906cc15154.js","a9a7754c-4cb8be3b2291d86156da.js","commons-ec4ac25f20428eb87e90.js","component---src-pages-index-tsx-d00045e999b340ebf4df.js"],"component---src-pages-search-tsx":["styles.6767fdfb70acbd36d207.css","cb1608f2-b629d79132906cc15154.js","commons-ec4ac25f20428eb87e90.js","component---src-pages-search-tsx-70c5457333e1350174a3.js"],"component---src-pages-tags-tsx":["styles.6767fdfb70acbd36d207.css","cb1608f2-b629d79132906cc15154.js","commons-ec4ac25f20428eb87e90.js","component---src-pages-tags-tsx-a7ae398fa8fb5bc2bcb2.js"],"component---src-templates-post-tsx":["styles.6767fdfb70acbd36d207.css","cb1608f2-b629d79132906cc15154.js","commons-ec4ac25f20428eb87e90.js","component---src-templates-post-tsx-67882746e97a6a94cad9.js"]},"childAssetsByChunkName":{}}