{"name":"build-javascript","namedChunkGroups":{"app":{"name":"app","assets":[{"name":"webpack-runtime.js","size":5079},{"name":"app.js","size":257511}],"filteredAssets":0,"assetsSize":262590,"filteredAuxiliaryAssets":2,"auxiliaryAssetsSize":936456},"component---src-pages-404-tsx":{"name":"component---src-pages-404-tsx","assets":[{"name":"styles.7c06ce3a9f6e4fd7e612.css","size":164603},{"name":"c66dc5f3.js","size":8114},{"name":"commons.js","size":138553},{"name":"component---src-pages-404-tsx.js","size":1239}],"filteredAssets":0,"assetsSize":312509,"filteredAuxiliaryAssets":61,"auxiliaryAssetsSize":6948221},"component---src-pages-index-tsx":{"name":"component---src-pages-index-tsx","assets":[{"name":"styles.7c06ce3a9f6e4fd7e612.css","size":164603},{"name":"c66dc5f3.js","size":8114},{"name":"c98cd720.js","size":5161},{"name":"commons.js","size":138553},{"name":"component---src-pages-index-tsx.js","size":4995}],"filteredAssets":0,"assetsSize":321426,"filteredAuxiliaryAssets":62,"auxiliaryAssetsSize":7354137},"component---src-pages-search-tsx":{"name":"component---src-pages-search-tsx","assets":[{"name":"styles.7c06ce3a9f6e4fd7e612.css","size":164603},{"name":"c66dc5f3.js","size":8114},{"name":"commons.js","size":138553},{"name":"component---src-pages-search-tsx.js","size":2929}],"filteredAssets":0,"assetsSize":314199,"filteredAuxiliaryAssets":61,"auxiliaryAssetsSize":6818451},"component---src-pages-tags-tsx":{"name":"component---src-pages-tags-tsx","assets":[{"name":"styles.7c06ce3a9f6e4fd7e612.css","size":164603},{"name":"c66dc5f3.js","size":8114},{"name":"commons.js","size":138553},{"name":"component---src-pages-tags-tsx.js","size":3203}],"filteredAssets":0,"assetsSize":314473,"filteredAuxiliaryAssets":61,"auxiliaryAssetsSize":6819355},"component---src-templates-post-tsx":{"name":"component---src-templates-post-tsx","assets":[{"name":"styles.7c06ce3a9f6e4fd7e612.css","size":164603},{"name":"c66dc5f3.js","size":8114},{"name":"d3a2d874.js","size":60438},{"name":"commons.js","size":138553},{"name":"component---src-templates-post-tsx.js","size":23922}],"filteredAssets":0,"assetsSize":395630,"filteredAuxiliaryAssets":62,"auxiliaryAssetsSize":7156220}},"assetsByChunkName":{"app":["webpack-runtime.js","app.js"],"component---src-pages-404-tsx":["styles.7c06ce3a9f6e4fd7e612.css","c66dc5f3.js","commons.js","component---src-pages-404-tsx.js"],"component---src-pages-index-tsx":["styles.7c06ce3a9f6e4fd7e612.css","c66dc5f3.js","c98cd720.js","commons.js","component---src-pages-index-tsx.js"],"component---src-pages-search-tsx":["styles.7c06ce3a9f6e4fd7e612.css","c66dc5f3.js","commons.js","component---src-pages-search-tsx.js"],"component---src-pages-tags-tsx":["styles.7c06ce3a9f6e4fd7e612.css","c66dc5f3.js","commons.js","component---src-pages-tags-tsx.js"],"component---src-templates-post-tsx":["styles.7c06ce3a9f6e4fd7e612.css","c66dc5f3.js","d3a2d874.js","commons.js","component---src-templates-post-tsx.js"]},"childAssetsByChunkName":{}}