{"name":"build-javascript","namedChunkGroups":{"app":{"name":"app","assets":[{"name":"webpack-runtime.js","size":5079},{"name":"app.js","size":256703}],"filteredAssets":0,"assetsSize":261782,"filteredAuxiliaryAssets":2,"auxiliaryAssetsSize":927143},"component---src-pages-404-tsx":{"name":"component---src-pages-404-tsx","assets":[{"name":"styles.cef636ff3d2f45070dd2.css","size":164513},{"name":"bbaffc7f.js","size":8111},{"name":"commons.js","size":138473},{"name":"component---src-pages-404-tsx.js","size":1239}],"filteredAssets":0,"assetsSize":312336,"filteredAuxiliaryAssets":61,"auxiliaryAssetsSize":6953980},"component---src-pages-index-tsx":{"name":"component---src-pages-index-tsx","assets":[{"name":"styles.cef636ff3d2f45070dd2.css","size":164513},{"name":"bbaffc7f.js","size":8111},{"name":"b5b08c4d.js","size":5161},{"name":"commons.js","size":138473},{"name":"component---src-pages-index-tsx.js","size":4980}],"filteredAssets":0,"assetsSize":321238,"filteredAuxiliaryAssets":62,"auxiliaryAssetsSize":7349285},"component---src-pages-search-tsx":{"name":"component---src-pages-search-tsx","assets":[{"name":"styles.cef636ff3d2f45070dd2.css","size":164513},{"name":"bbaffc7f.js","size":8111},{"name":"commons.js","size":138473},{"name":"component---src-pages-search-tsx.js","size":2918}],"filteredAssets":0,"assetsSize":314015,"filteredAuxiliaryAssets":61,"auxiliaryAssetsSize":6821135},"component---src-pages-tags-tsx":{"name":"component---src-pages-tags-tsx","assets":[{"name":"styles.cef636ff3d2f45070dd2.css","size":164513},{"name":"bbaffc7f.js","size":8111},{"name":"commons.js","size":138473},{"name":"component---src-pages-tags-tsx.js","size":3189}],"filteredAssets":0,"assetsSize":314286,"filteredAuxiliaryAssets":61,"auxiliaryAssetsSize":6822032},"component---src-templates-post-tsx":{"name":"component---src-templates-post-tsx","assets":[{"name":"styles.cef636ff3d2f45070dd2.css","size":164513},{"name":"bbaffc7f.js","size":8111},{"name":"d3a2d874.js","size":60438},{"name":"commons.js","size":138473},{"name":"component---src-templates-post-tsx.js","size":23975}],"filteredAssets":0,"assetsSize":395510,"filteredAuxiliaryAssets":62,"auxiliaryAssetsSize":7159010}},"assetsByChunkName":{"app":["webpack-runtime.js","app.js"],"component---src-pages-404-tsx":["styles.cef636ff3d2f45070dd2.css","bbaffc7f.js","commons.js","component---src-pages-404-tsx.js"],"component---src-pages-index-tsx":["styles.cef636ff3d2f45070dd2.css","bbaffc7f.js","b5b08c4d.js","commons.js","component---src-pages-index-tsx.js"],"component---src-pages-search-tsx":["styles.cef636ff3d2f45070dd2.css","bbaffc7f.js","commons.js","component---src-pages-search-tsx.js"],"component---src-pages-tags-tsx":["styles.cef636ff3d2f45070dd2.css","bbaffc7f.js","commons.js","component---src-pages-tags-tsx.js"],"component---src-templates-post-tsx":["styles.cef636ff3d2f45070dd2.css","bbaffc7f.js","d3a2d874.js","commons.js","component---src-templates-post-tsx.js"]},"childAssetsByChunkName":{}}