{"name":"build-javascript","namedChunkGroups":{"app":{"name":"app","assets":[{"name":"webpack-runtime-99da1c2d99a6b3a0eaaa.js","size":5475},{"name":"framework-435f04c43d328656abd0.js","size":129756},{"name":"app-92a7fd11ac2be89ca284.js","size":108946}],"filteredAssets":0,"assetsSize":244177,"filteredAuxiliaryAssets":3,"auxiliaryAssetsSize":874926},"component---src-pages-404-tsx":{"name":"component---src-pages-404-tsx","assets":[{"name":"styles.be11f01d8962aad93775.css","size":142335},{"name":"45040cdc-da0d13c2de73ad0a45dd.js","size":10743},{"name":"03ad9d84-2aa91fb580eb8b248956.js","size":1163},{"name":"commons-231fe8439299c8a77870.js","size":136380},{"name":"component---src-pages-404-tsx-bf45d9c06f3cce83e175.js","size":761}],"filteredAssets":0,"assetsSize":291382,"filteredAuxiliaryAssets":78,"auxiliaryAssetsSize":14875759},"component---src-pages-index-tsx":{"name":"component---src-pages-index-tsx","assets":[{"name":"styles.be11f01d8962aad93775.css","size":142335},{"name":"45040cdc-da0d13c2de73ad0a45dd.js","size":10743},{"name":"c4557d04-167609f43ae32062d3d3.js","size":5218},{"name":"commons-231fe8439299c8a77870.js","size":136380},{"name":"component---src-pages-index-tsx-782d68e48c5ba46c9a52.js","size":5005}],"filteredAssets":0,"assetsSize":299681,"filteredAuxiliaryAssets":78,"auxiliaryAssetsSize":15232917},"component---src-pages-search-tsx":{"name":"component---src-pages-search-tsx","assets":[{"name":"styles.be11f01d8962aad93775.css","size":142335},{"name":"45040cdc-da0d13c2de73ad0a45dd.js","size":10743},{"name":"commons-231fe8439299c8a77870.js","size":136380},{"name":"component---src-pages-search-tsx-5d23cdf170db3777cc84.js","size":2943}],"filteredAssets":0,"assetsSize":292401,"filteredAuxiliaryAssets":77,"auxiliaryAssetsSize":14712625},"component---src-pages-tags-tsx":{"name":"component---src-pages-tags-tsx","assets":[{"name":"styles.be11f01d8962aad93775.css","size":142335},{"name":"45040cdc-da0d13c2de73ad0a45dd.js","size":10743},{"name":"commons-231fe8439299c8a77870.js","size":136380},{"name":"component---src-pages-tags-tsx-8627d84ba51251bf38f5.js","size":3214}],"filteredAssets":0,"assetsSize":292672,"filteredAuxiliaryAssets":77,"auxiliaryAssetsSize":14713493},"component---src-templates-post-tsx":{"name":"component---src-templates-post-tsx","assets":[{"name":"styles.be11f01d8962aad93775.css","size":142335},{"name":"45040cdc-da0d13c2de73ad0a45dd.js","size":10743},{"name":"d3a2d874-4dca7a15fb69d868c6ef.js","size":60480},{"name":"commons-231fe8439299c8a77870.js","size":136380},{"name":"component---src-templates-post-tsx-60a7d7b16c34ba8d9e2c.js","size":23382}],"filteredAssets":0,"assetsSize":373320,"filteredAuxiliaryAssets":78,"auxiliaryAssetsSize":15049592}},"assetsByChunkName":{"app":["webpack-runtime-99da1c2d99a6b3a0eaaa.js","framework-435f04c43d328656abd0.js","app-92a7fd11ac2be89ca284.js"],"component---src-pages-404-tsx":["styles.be11f01d8962aad93775.css","45040cdc-da0d13c2de73ad0a45dd.js","03ad9d84-2aa91fb580eb8b248956.js","commons-231fe8439299c8a77870.js","component---src-pages-404-tsx-bf45d9c06f3cce83e175.js"],"component---src-pages-index-tsx":["styles.be11f01d8962aad93775.css","45040cdc-da0d13c2de73ad0a45dd.js","c4557d04-167609f43ae32062d3d3.js","commons-231fe8439299c8a77870.js","component---src-pages-index-tsx-782d68e48c5ba46c9a52.js"],"component---src-pages-search-tsx":["styles.be11f01d8962aad93775.css","45040cdc-da0d13c2de73ad0a45dd.js","commons-231fe8439299c8a77870.js","component---src-pages-search-tsx-5d23cdf170db3777cc84.js"],"component---src-pages-tags-tsx":["styles.be11f01d8962aad93775.css","45040cdc-da0d13c2de73ad0a45dd.js","commons-231fe8439299c8a77870.js","component---src-pages-tags-tsx-8627d84ba51251bf38f5.js"],"component---src-templates-post-tsx":["styles.be11f01d8962aad93775.css","45040cdc-da0d13c2de73ad0a45dd.js","d3a2d874-4dca7a15fb69d868c6ef.js","commons-231fe8439299c8a77870.js","component---src-templates-post-tsx-60a7d7b16c34ba8d9e2c.js"]},"childAssetsByChunkName":{}}